gmaps_scraper/__init__.py
gmaps_scraper/geo_utils.py
gmaps_scraper/gmaps.py
gmaps_scraper/tkinter_utils.py
gmaps_scraper-0.4.4.dist-info/licenses/LICENSE
gmaps_scraper-0.4.4.dist-info/METADATA
gmaps_scraper-0.4.4.dist-info/WHEEL
gmaps_scraper-0.4.4.dist-info/top_level.txt
gmaps_scraper-0.4.4.dist-info/RECORD
