Metadata-Version: 2.4
Name: gmaps-scraper
Version: 0.4.4
Summary: Interactive Google Maps scraper with Tkinter confirmation
Author-email: "Kanad Rishiraj (RoamingSaint)" <roamingsaint27@gmail.com>
License-Expression: MIT
Requires-Python: >=3.7
License-File: LICENSE
Requires-Dist: pycountry
Requires-Dist: colorfulPyPrint
Requires-Dist: reverse_geocoder
Requires-Dist: selenium-web-automation-utils
Dynamic: license-file
